LICENSE
README.md
manifest/__init__.py
manifest/constants.py
manifest/decorator.py
manifest/exc.py
manifest/initialize.py
manifest/llm/__init__.py
manifest/llm/base.py
manifest/llm/openai.py
manifest/parser.py
manifest/serde.py
manifest/templates/anthropic/call.j2
manifest/templates/anthropic/system.j2
manifest/templates/openai/call.j2
manifest/templates/openai/system.j2
manifest/tmpl.py
manifest/types/service.py
manifest/utils/__init__.py
manifest/utils/args.py
manifest/utils/asset.py
manifest/utils/types.py
manifest-0.6.0.dist-info/LICENSE
manifest-0.6.0.dist-info/METADATA
manifest-0.6.0.dist-info/WHEEL
manifest-0.6.0.dist-info/RECORD
