Metadata-Version: 2.1
Name: manifest
Version: 0.6.0
Summary: Use an LLM to execute code
Home-page: https://github.com/amoffat/manifest
License: MIT
Keywords: llm,ai
Author: Andrew Moffat
Author-email: arwmoffat@gmail.com
Requires-Python: >=3.11,<4.0
Classifier: Development Status :: 4 - Beta
Classifier: Intended Audience :: Developers
Classifier: License :: OSI Approved :: MIT License
Classifier: Programming Language :: Python
Classifier: Programming Language :: Python :: 3
Classifier: Programming Language :: Python :: 3.11
Classifier: Programming Language :: Python :: 3.12
Classifier: Topic :: Software Development :: Libraries :: Python Modules
Requires-Dist: jinja2 (>=3.1.4,<4.0.0)
Requires-Dist: jsonschema (>=4.23.0,<5.0.0)
Requires-Dist: lxml (>=5.2.2,<6.0.0)
Requires-Dist: openai (>=1.40.1,<2.0.0)
Requires-Dist: python-dotenv (>=1.0.1,<2.0.0)
Project-URL: Repository, https://github.com/amoffat/manifest
